MP_Calculator/__init__.py
MP_Calculator/add.py
MP_Calculator/subtract.py
MP_Calculator/extras/__init__.py
MP_Calculator/extras/divide.py
MP_Calculator/extras/multiply.py
MP_Calculator/extras/power.py
MP_Calculator-0.0.1.dist-info/METADATA
MP_Calculator-0.0.1.dist-info/WHEEL
MP_Calculator-0.0.1.dist-info/top_level.txt
MP_Calculator-0.0.1.dist-info/RECORD
